simpy/__init__.py
simpy/core.py
simpy/events.py
simpy/exceptions.py
simpy/py.typed
simpy/rt.py
simpy/util.py
simpy/resources/__init__.py
simpy/resources/base.py
simpy/resources/container.py
simpy/resources/resource.py
simpy/resources/store.py
simpy-4.1.0.dist-info/LICENSE.rst
simpy-4.1.0.dist-info/METADATA
simpy-4.1.0.dist-info/WHEEL
simpy-4.1.0.dist-info/top_level.txt
simpy-4.1.0.dist-info/RECORD
