Metadata-Version: 2.1
Name: simpy
Version: 4.1.0
Summary: Event discrete, process based simulation for Python.
Author-email: Ontje Lünsdorf <the_com@gmx.de>, Stefan Scherfke <stefan@sofa-rockers.org>
License: MIT
Project-URL: Homepage, https://simpy.readthedocs.io
Project-URL: Documentation, https://simpy.readthedocs.io
Project-URL: Source code, https://gitlab.com/team-simpy/simpy/
Classifier: Development Status :: 5 - Production/Stable
Classifier: Environment :: Console
Classifier: Intended Audience :: Developers
Classifier: Intended Audience :: Education
Classifier: Intended Audience :: Science/Research
Classifier: License :: OSI Approved :: MIT License
Classifier: Natural Language :: English
Classifier: Operating System :: OS Independent
Classifier: Programming Language :: Python
Classifier: Programming Language :: Python :: 3
Classifier: Programming Language :: Python :: 3.8
Classifier: Programming Language :: Python :: 3.9
Classifier: Programming Language :: Python :: 3.10
Classifier: Programming Language :: Python :: 3.11
Classifier: Programming Language :: Python :: 3.12
Classifier: Programming Language :: Python :: Implementation :: CPython
Classifier: Programming Language :: Python :: Implementation :: PyPy
Classifier: Topic :: Scientific/Engineering
Requires-Python: >=3.8
License-File: LICENSE.rst
